rigctl_client.py
server.py
rigctl_mcp-1.1.0.dist-info/METADATA
rigctl_mcp-1.1.0.dist-info/WHEEL
rigctl_mcp-1.1.0.dist-info/entry_points.txt
rigctl_mcp-1.1.0.dist-info/top_level.txt
rigctl_mcp-1.1.0.dist-info/RECORD
