Metadata-Version: 2.4
Name: rigctl-mcp
Version: 1.1.0
Summary: MCP server for Hamlib rigctl radio control
Author: Zappatta
Project-URL: Homepage, https://github.com/yourusername/rigctl-mcp
Project-URL: Repository, https://github.com/yourusername/rigctl-mcp
Project-URL: Issues, https://github.com/yourusername/rigctl-mcp/issues
Keywords: mcp,rigctl,hamlib,sdr,radio,sdr++
Classifier: Development Status :: 4 - Beta
Classifier: Intended Audience :: Developers
Classifier: Programming Language :: Python :: 3
Classifier: Programming Language :: Python :: 3.10
Classifier: Programming Language :: Python :: 3.11
Classifier: Programming Language :: Python :: 3.12
Requires-Python: >=3.10
Requires-Dist: mcp>=0.1.0
Dynamic: requires-python
